{"nodes": [{"id": "d_website_portal_abk_ciraya_src_pages_kpipage_tsx", "label": "KPIPage.tsx", "file_type": "code", "source_file": "D:\\website\\portal-abk-ciraya\\src\\pages\\KPIPage.tsx", "source_location": "L1"}, {"id": "pages_kpipage_getstatusbadge", "label": "getStatusBadge()", "file_type": "code", "source_file": "D:\\website\\portal-abk-ciraya\\src\\pages\\KPIPage.tsx", "source_location": "L27"}, {"id": "pages_kpipage_getprogresscolor", "label": "getProgressColor()", "file_type": "code", "source_file": "D:\\website\\portal-abk-ciraya\\src\\pages\\KPIPage.tsx", "source_location": "L40"}], "edges": [{"source": "d_website_portal_abk_ciraya_src_pages_kpipage_tsx", "target": "react", "relation": "imports_from", "confidence": "EXTRACTED", "source_file": "D:\\website\\portal-abk-ciraya\\src\\pages\\KPIPage.tsx", "source_location": "L1", "weight": 1.0}, {"source": "d_website_portal_abk_ciraya_src_pages_kpipage_tsx", "target": "lucide_react", "relation": "imports_from", "confidence": "EXTRACTED", "source_file": "D:\\website\\portal-abk-ciraya\\src\\pages\\KPIPage.tsx", "source_location": "L2", "weight": 1.0}, {"source": "d_website_portal_abk_ciraya_src_pages_kpipage_tsx", "target": "d_website_portal_abk_ciraya_src_components_layout_header", "relation": "imports_from", "confidence": "EXTRACTED", "source_file": "D:\\website\\portal-abk-ciraya\\src\\pages\\KPIPage.tsx", "source_location": "L3", "weight": 1.0}, {"source": "d_website_portal_abk_ciraya_src_pages_kpipage_tsx", "target": "d_website_portal_abk_ciraya_src_components_ui_index", "relation": "imports_from", "confidence": "EXTRACTED", "source_file": "D:\\website\\portal-abk-ciraya\\src\\pages\\KPIPage.tsx", "source_location": "L4", "weight": 1.0}, {"source": "d_website_portal_abk_ciraya_src_pages_kpipage_tsx", "target": "react_chartjs_2", "relation": "imports_from", "confidence": "EXTRACTED", "source_file": "D:\\website\\portal-abk-ciraya\\src\\pages\\KPIPage.tsx", "source_location": "L5", "weight": 1.0}, {"source": "d_website_portal_abk_ciraya_src_pages_kpipage_tsx", "target": "pages_kpipage_getstatusbadge", "relation": "contains", "confidence": "EXTRACTED", "source_file": "D:\\website\\portal-abk-ciraya\\src\\pages\\KPIPage.tsx", "source_location": "L27", "weight": 1.0}, {"source": "d_website_portal_abk_ciraya_src_pages_kpipage_tsx", "target": "pages_kpipage_getprogresscolor", "relation": "contains", "confidence": "EXTRACTED", "source_file": "D:\\website\\portal-abk-ciraya\\src\\pages\\KPIPage.tsx", "source_location": "L40", "weight": 1.0}], "raw_calls": []}